feco3-0.5.0.dist-info/METADATA
feco3-0.5.0.dist-info/WHEEL
feco3/_version.py
feco3/__init__.py
feco3/_feco3.pypy38-pp73-arm-linux-gnu.so
feco3-0.5.0.dist-info/RECORD
