Metadata-Version: 2.1
Name: feco3
Version: 0.5.0
Classifier: Programming Language :: Rust
Classifier: Programming Language :: Python :: Implementation :: CPython
Classifier: Programming Language :: Python :: Implementation :: PyPy
Classifier: Development Status :: 3 - Alpha
Classifier: Intended Audience :: Developers
Classifier: License :: OSI Approved :: Apache Software License
Classifier: Topic :: File Formats
Classifier: Topic :: Office/Business :: Financial
Classifier: Topic :: Text Processing
Requires-Dist: importlib_metadata ; python_version < '3.8'
Requires-Dist: pyarrow ; extra == 'arrow'
Provides-Extra: arrow
Summary: A Rust-backed Python library for parsing .fec files.
Keywords: fec,fec-file,rust,pyo3,arrow,pyarrow
Author-email: Nick Crews <nicholas.b.crews@gmail.com>
Requires-Python: >=3.7
Project-URL: Documentation, https://nickcrews.github.io/feco3/
Project-URL: Repository, https://github.com/NickCrews/feco3
